delimiter_name_extract.py
delimiter_name_extract-1.0.dist-info/METADATA
delimiter_name_extract-1.0.dist-info/WHEEL
delimiter_name_extract-1.0.dist-info/RECORD
